{
  "type": "issue",
  "issue": {
    "id": 6117366,
    "node_id": "MDU6SXNzdWU2MTE3MzY2",
    "url": "https://api.github.com/repos/bitcoin/bitcoin/issues/1664",
    "repository_url": "https://api.github.com/repos/bitcoin/bitcoin",
    "labels_url": "https://api.github.com/repos/bitcoin/bitcoin/issues/1664/labels%7B/name%7D",
    "comments_url": "https://api.github.com/repos/bitcoin/bitcoin/issues/1664/comments",
    "events_url": "https://api.github.com/repos/bitcoin/bitcoin/issues/1664/events",
    "html_url": "https://github.com/bitcoin/bitcoin/issues/1664",
    "number": 1664,
    "state": "closed",
    "state_reason": "completed",
    "title": "bitcoin-qt -noconnect uses 100% CPU",
    "body": "Maybe I'm doing it wrong, but if I specify \"-noconnect\" in an attempt to have bitcoin-qt not connect to any peers, the ThreadOpenConnections2() function goes into a tight loop that runs forever.\n\nThe following 1-line change fixes the problem:\n\n```\ndiff --git a/src/net.cpp b/src/net.cpp\nindex e10829a..fe1712a 100644\n--- a/src/net.cpp\n+++ b/src/net.cpp\n@@ -1367,7 +1367,7 @@ void ThreadOpenConnections2(void* parg)\n     printf(\"ThreadOpenConnections started\\n\");\n\n     // Connect to specific addresses\n-    if (mapArgs.count(\"-connect\"))\n+    if (mapArgs.count(\"-connect\") && mapMultiArgs[\"-connect\"].size())\n     {\n         for (int64 nLoop = 0;; nLoop++)\n         {\n```\n",
    "user": {
      "login": "dooglus",
      "id": 573356,
      "node_id": "MDQ6VXNlcjU3MzM1Ng==",
      "avatar_url": "https://avatars.githubusercontent.com/u/573356?v=4",
      "gravatar_id": "",
      "url": "https://api.github.com/users/dooglus",
      "html_url": "https://github.com/dooglus",
      "followers_url": "https://api.github.com/users/dooglus/followers",
      "following_url": "https://api.github.com/users/dooglus/following%7B/other_user%7D",
      "gists_url": "https://api.github.com/users/dooglus/gists%7B/gist_id%7D",
      "starred_url": "https://api.github.com/users/dooglus/starred%7B/owner%7D%7B/repo%7D",
      "subscriptions_url": "https://api.github.com/users/dooglus/subscriptions",
      "organizations_url": "https://api.github.com/users/dooglus/orgs",
      "repos_url": "https://api.github.com/users/dooglus/repos",
      "events_url": "https://api.github.com/users/dooglus/events%7B/privacy%7D",
      "received_events_url": "https://api.github.com/users/dooglus/received_events",
      "type": "User",
      "site_admin": false
    },
    "labels": [],
    "assignees": [],
    "author_association": "CONTRIBUTOR",
    "locked": true,
    "active_lock_reason": "resolved",
    "comments": 11,
    "closed_at": "2013-10-26T08:02:54Z",
    "created_at": "2012-08-09T01:00:09Z",
    "updated_at": "2021-09-08T12:32:15Z"
  },
  "events": [
    {
      "event": "commented",
      "id": 7603086,
      "node_id": "MDEyOklzc3VlQ29tbWVudDc2MDMwODY=",
      "url": "https://api.github.com/repos/bitcoin/bitcoin/issues/comments/7603086",
      "actor": {
        "login": "luke-jr",
        "id": 1095675,
        "node_id": "MDQ6VXNlcjEwOTU2NzU=",
        "avatar_url": "https://avatars.githubusercontent.com/u/1095675?v=4",
        "gravatar_id": "",
        "url": "https://api.github.com/users/luke-jr",
        "html_url": "https://github.com/luke-jr",
        "followers_url": "https://api.github.com/users/luke-jr/followers",
        "following_url": "https://api.github.com/users/luke-jr/following%7B/other_user%7D",
        "gists_url": "https://api.github.com/users/luke-jr/gists%7B/gist_id%7D",
        "starred_url": "https://api.github.com/users/luke-jr/starred%7B/owner%7D%7B/repo%7D",
        "subscriptions_url": "https://api.github.com/users/luke-jr/subscriptions",
        "organizations_url": "https://api.github.com/users/luke-jr/orgs",
        "repos_url": "https://api.github.com/users/luke-jr/repos",
        "events_url": "https://api.github.com/users/luke-jr/events%7B/privacy%7D",
        "received_events_url": "https://api.github.com/users/luke-jr/received_events",
        "type": "User",
        "site_admin": false
      },
      "commit_id": null,
      "commit_url": null,
      "created_at": "2012-08-09T01:40:01Z",
      "updated_at": "2012-08-09T01:40:01Z",
      "author_association": "MEMBER",
      "body": "I don't think -noconnect was ever supported as a valid option.\n",
      "user": {
        "login": "luke-jr",
        "id": 1095675,
        "node_id": "MDQ6VXNlcjEwOTU2NzU=",
        "avatar_url": "https://avatars.githubusercontent.com/u/1095675?v=4",
        "gravatar_id": "",
        "url": "https://api.github.com/users/luke-jr",
        "html_url": "https://github.com/luke-jr",
        "followers_url": "https://api.github.com/users/luke-jr/followers",
        "following_url": "https://api.github.com/users/luke-jr/following%7B/other_user%7D",
        "gists_url": "https://api.github.com/users/luke-jr/gists%7B/gist_id%7D",
        "starred_url": "https://api.github.com/users/luke-jr/starred%7B/owner%7D%7B/repo%7D",
        "subscriptions_url": "https://api.github.com/users/luke-jr/subscriptions",
        "organizations_url": "https://api.github.com/users/luke-jr/orgs",
        "repos_url": "https://api.github.com/users/luke-jr/repos",
        "events_url": "https://api.github.com/users/luke-jr/events%7B/privacy%7D",
        "received_events_url": "https://api.github.com/users/luke-jr/received_events",
        "type": "User",
        "site_admin": false
      },
      "html_url": "https://github.com/bitcoin/bitcoin/issues/1664#issuecomment-7603086",
      "issue_url": "https://api.github.com/repos/bitcoin/bitcoin/issues/1664"
    },
    {
      "event": "commented",
      "id": 7603214,
      "node_id": "MDEyOklzc3VlQ29tbWVudDc2MDMyMTQ=",
      "url": "https://api.github.com/repos/bitcoin/bitcoin/issues/comments/7603214",
      "actor": {
        "login": "gmaxwell",
        "id": 858454,
        "node_id": "MDQ6VXNlcjg1ODQ1NA==",
        "avatar_url": "https://avatars.githubusercontent.com/u/858454?v=4",
        "gravatar_id": "",
        "url": "https://api.github.com/users/gmaxwell",
        "html_url": "https://github.com/gmaxwell",
        "followers_url": "https://api.github.com/users/gmaxwell/followers",
        "following_url": "https://api.github.com/users/gmaxwell/following%7B/other_user%7D",
        "gists_url": "https://api.github.com/users/gmaxwell/gists%7B/gist_id%7D",
        "starred_url": "https://api.github.com/users/gmaxwell/starred%7B/owner%7D%7B/repo%7D",
        "subscriptions_url": "https://api.github.com/users/gmaxwell/subscriptions",
        "organizations_url": "https://api.github.com/users/gmaxwell/orgs",
        "repos_url": "https://api.github.com/users/gmaxwell/repos",
        "events_url": "https://api.github.com/users/gmaxwell/events%7B/privacy%7D",
        "received_events_url": "https://api.github.com/users/gmaxwell/received_events",
        "type": "User",
        "site_admin": false
      },
      "commit_id": null,
      "commit_url": null,
      "created_at": "2012-08-09T01:48:37Z",
      "updated_at": "2012-08-09T01:48:37Z",
      "author_association": "CONTRIBUTOR",
      "body": "As Luke says, that wasn't an intended option as far as I know. But it sounds like a reasonable thing to support, though we should probably also audit the other cases were a no wasn't really anticipated.\n",
      "user": {
        "login": "gmaxwell",
        "id": 858454,
        "node_id": "MDQ6VXNlcjg1ODQ1NA==",
        "avatar_url": "https://avatars.githubusercontent.com/u/858454?v=4",
        "gravatar_id": "",
        "url": "https://api.github.com/users/gmaxwell",
        "html_url": "https://github.com/gmaxwell",
        "followers_url": "https://api.github.com/users/gmaxwell/followers",
        "following_url": "https://api.github.com/users/gmaxwell/following%7B/other_user%7D",
        "gists_url": "https://api.github.com/users/gmaxwell/gists%7B/gist_id%7D",
        "starred_url": "https://api.github.com/users/gmaxwell/starred%7B/owner%7D%7B/repo%7D",
        "subscriptions_url": "https://api.github.com/users/gmaxwell/subscriptions",
        "organizations_url": "https://api.github.com/users/gmaxwell/orgs",
        "repos_url": "https://api.github.com/users/gmaxwell/repos",
        "events_url": "https://api.github.com/users/gmaxwell/events%7B/privacy%7D",
        "received_events_url": "https://api.github.com/users/gmaxwell/received_events",
        "type": "User",
        "site_admin": false
      },
      "html_url": "https://github.com/bitcoin/bitcoin/issues/1664#issuecomment-7603214",
      "issue_url": "https://api.github.com/repos/bitcoin/bitcoin/issues/1664"
    },
    {
      "event": "commented",
      "id": 7843758,
      "node_id": "MDEyOklzc3VlQ29tbWVudDc4NDM3NTg=",
      "url": "https://api.github.com/repos/bitcoin/bitcoin/issues/comments/7843758",
      "actor": {
        "login": "laanwj",
        "id": 126646,
        "node_id": "MDQ6VXNlcjEyNjY0Ng==",
        "avatar_url": "https://avatars.githubusercontent.com/u/126646?v=4",
        "gravatar_id": "",
        "url": "https://api.github.com/users/laanwj",
        "html_url": "https://github.com/laanwj",
        "followers_url": "https://api.github.com/users/laanwj/followers",
        "following_url": "https://api.github.com/users/laanwj/following%7B/other_user%7D",
        "gists_url": "https://api.github.com/users/laanwj/gists%7B/gist_id%7D",
        "starred_url": "https://api.github.com/users/laanwj/starred%7B/owner%7D%7B/repo%7D",
        "subscriptions_url": "https://api.github.com/users/laanwj/subscriptions",
        "organizations_url": "https://api.github.com/users/laanwj/orgs",
        "repos_url": "https://api.github.com/users/laanwj/repos",
        "events_url": "https://api.github.com/users/laanwj/events%7B/privacy%7D",
        "received_events_url": "https://api.github.com/users/laanwj/received_events",
        "type": "User",
        "site_admin": false
      },
      "commit_id": null,
      "commit_url": null,
      "created_at": "2012-08-18T11:18:19Z",
      "updated_at": "2012-08-18T12:39:36Z",
      "author_association": "MEMBER",
      "body": "This also appears to happen when it simply has no nodes to connect to, even without -noconnect.  In my case I have a testnet node that has no addresses to connect to, so it keeps cycling through them and the \"bitcoin-opencon\" thread takes a lot of CPU time.\n\nIn my case, it keeps selecting the same peer every half a second (with a nonstandard port #, so after 50 tries), trying to connect to it:\n\n```\ntrying connection XX.XX.XX.XX:18334 lastseen=1542.8hrs\nconnect() failed after select(): Connection refused\n```\n\nNot yet sure why that takes so much CPU usage %, though, as the thread sleeps mostly.\n\nEdit: According to callgrind, most time is spent inside CAddrMan::Select(int), calling CAddrMan::Select_(int), calling GetRandInt(int). \n\nIs that random function so expensive? I think so, after changing to simply use rand(), putting at the top of addrman.cpp a hack\n\n```\n#define GetRandInt(x) (rand()%(x))\n```\n\nThe CPU usage dropped back to 4% only. Still significant, but not close to holding up a core. Using rand might be good enough here, as there is no need for cryptographically secure number here. See also issue #1057.\n\nAnyway, using something like exponential backoff in the connection thread is probably the real fix. Just wanted to know why peer selection was so expensive.\n",
      "user": {
        "login": "laanwj",
        "id": 126646,
        "node_id": "MDQ6VXNlcjEyNjY0Ng==",
        "avatar_url": "https://avatars.githubusercontent.com/u/126646?v=4",
        "gravatar_id": "",
        "url": "https://api.github.com/users/laanwj",
        "html_url": "https://github.com/laanwj",
        "followers_url": "https://api.github.com/users/laanwj/followers",
        "following_url": "https://api.github.com/users/laanwj/following%7B/other_user%7D",
        "gists_url": "https://api.github.com/users/laanwj/gists%7B/gist_id%7D",
        "starred_url": "https://api.github.com/users/laanwj/starred%7B/owner%7D%7B/repo%7D",
        "subscriptions_url": "https://api.github.com/users/laanwj/subscriptions",
        "organizations_url": "https://api.github.com/users/laanwj/orgs",
        "repos_url": "https://api.github.com/users/laanwj/repos",
        "events_url": "https://api.github.com/users/laanwj/events%7B/privacy%7D",
        "received_events_url": "https://api.github.com/users/laanwj/received_events",
        "type": "User",
        "site_admin": false
      },
      "html_url": "https://github.com/bitcoin/bitcoin/issues/1664#issuecomment-7843758",
      "issue_url": "https://api.github.com/repos/bitcoin/bitcoin/issues/1664"
    },
    {
      "event": "commented",
      "id": 8680801,
      "node_id": "MDEyOklzc3VlQ29tbWVudDg2ODA4MDE=",
      "url": "https://api.github.com/repos/bitcoin/bitcoin/issues/comments/8680801",
      "actor": {
        "login": "laanwj",
        "id": 126646,
        "node_id": "MDQ6VXNlcjEyNjY0Ng==",
        "avatar_url": "https://avatars.githubusercontent.com/u/126646?v=4",
        "gravatar_id": "",
        "url": "https://api.github.com/users/laanwj",
        "html_url": "https://github.com/laanwj",
        "followers_url": "https://api.github.com/users/laanwj/followers",
        "following_url": "https://api.github.com/users/laanwj/following%7B/other_user%7D",
        "gists_url": "https://api.github.com/users/laanwj/gists%7B/gist_id%7D",
        "starred_url": "https://api.github.com/users/laanwj/starred%7B/owner%7D%7B/repo%7D",
        "subscriptions_url": "https://api.github.com/users/laanwj/subscriptions",
        "organizations_url": "https://api.github.com/users/laanwj/orgs",
        "repos_url": "https://api.github.com/users/laanwj/repos",
        "events_url": "https://api.github.com/users/laanwj/events%7B/privacy%7D",
        "received_events_url": "https://api.github.com/users/laanwj/received_events",
        "type": "User",
        "site_admin": false
      },
      "commit_id": null,
      "commit_url": null,
      "created_at": "2012-09-19T06:50:05Z",
      "updated_at": "2012-09-19T06:50:05Z",
      "author_association": "MEMBER",
      "body": "Is this fixed in 0.7.0?\n",
      "user": {
        "login": "laanwj",
        "id": 126646,
        "node_id": "MDQ6VXNlcjEyNjY0Ng==",
        "avatar_url": "https://avatars.githubusercontent.com/u/126646?v=4",
        "gravatar_id": "",
        "url": "https://api.github.com/users/laanwj",
        "html_url": "https://github.com/laanwj",
        "followers_url": "https://api.github.com/users/laanwj/followers",
        "following_url": "https://api.github.com/users/laanwj/following%7B/other_user%7D",
        "gists_url": "https://api.github.com/users/laanwj/gists%7B/gist_id%7D",
        "starred_url": "https://api.github.com/users/laanwj/starred%7B/owner%7D%7B/repo%7D",
        "subscriptions_url": "https://api.github.com/users/laanwj/subscriptions",
        "organizations_url": "https://api.github.com/users/laanwj/orgs",
        "repos_url": "https://api.github.com/users/laanwj/repos",
        "events_url": "https://api.github.com/users/laanwj/events%7B/privacy%7D",
        "received_events_url": "https://api.github.com/users/laanwj/received_events",
        "type": "User",
        "site_admin": false
      },
      "html_url": "https://github.com/bitcoin/bitcoin/issues/1664#issuecomment-8680801",
      "issue_url": "https://api.github.com/repos/bitcoin/bitcoin/issues/1664"
    },
    {
      "event": "commented",
      "id": 8700825,
      "node_id": "MDEyOklzc3VlQ29tbWVudDg3MDA4MjU=",
      "url": "https://api.github.com/repos/bitcoin/bitcoin/issues/comments/8700825",
      "actor": {
        "login": "dooglus",
        "id": 573356,
        "node_id": "MDQ6VXNlcjU3MzM1Ng==",
        "avatar_url": "https://avatars.githubusercontent.com/u/573356?v=4",
        "gravatar_id": "",
        "url": "https://api.github.com/users/dooglus",
        "html_url": "https://github.com/dooglus",
        "followers_url": "https://api.github.com/users/dooglus/followers",
        "following_url": "https://api.github.com/users/dooglus/following%7B/other_user%7D",
        "gists_url": "https://api.github.com/users/dooglus/gists%7B/gist_id%7D",
        "starred_url": "https://api.github.com/users/dooglus/starred%7B/owner%7D%7B/repo%7D",
        "subscriptions_url": "https://api.github.com/users/dooglus/subscriptions",
        "organizations_url": "https://api.github.com/users/dooglus/orgs",
        "repos_url": "https://api.github.com/users/dooglus/repos",
        "events_url": "https://api.github.com/users/dooglus/events%7B/privacy%7D",
        "received_events_url": "https://api.github.com/users/dooglus/received_events",
        "type": "User",
        "site_admin": false
      },
      "commit_id": null,
      "commit_url": null,
      "created_at": "2012-09-19T18:15:56Z",
      "updated_at": "2012-09-19T18:15:56Z",
      "author_association": "CONTRIBUTOR",
      "body": "It doesn't use 100% CPU, but it doesn't work either - it still tries to connect:\n\n```\n(gdb) run -server -nolisten -noconnect\n[...]\nBitcoin version v0.7.0rc3-dirty-beta (2012-09-12 14:07:22 -0400)\n[...]\ntrying connection 92.240.248.99:8333 lastseen=2.7hrs\nconnected 92.240.248.99:8333\n```\n",
      "user": {
        "login": "dooglus",
        "id": 573356,
        "node_id": "MDQ6VXNlcjU3MzM1Ng==",
        "avatar_url": "https://avatars.githubusercontent.com/u/573356?v=4",
        "gravatar_id": "",
        "url": "https://api.github.com/users/dooglus",
        "html_url": "https://github.com/dooglus",
        "followers_url": "https://api.github.com/users/dooglus/followers",
        "following_url": "https://api.github.com/users/dooglus/following%7B/other_user%7D",
        "gists_url": "https://api.github.com/users/dooglus/gists%7B/gist_id%7D",
        "starred_url": "https://api.github.com/users/dooglus/starred%7B/owner%7D%7B/repo%7D",
        "subscriptions_url": "https://api.github.com/users/dooglus/subscriptions",
        "organizations_url": "https://api.github.com/users/dooglus/orgs",
        "repos_url": "https://api.github.com/users/dooglus/repos",
        "events_url": "https://api.github.com/users/dooglus/events%7B/privacy%7D",
        "received_events_url": "https://api.github.com/users/dooglus/received_events",
        "type": "User",
        "site_admin": false
      },
      "html_url": "https://github.com/bitcoin/bitcoin/issues/1664#issuecomment-8700825",
      "issue_url": "https://api.github.com/repos/bitcoin/bitcoin/issues/1664"
    },
    {
      "event": "commented",
      "id": 8700945,
      "node_id": "MDEyOklzc3VlQ29tbWVudDg3MDA5NDU=",
      "url": "https://api.github.com/repos/bitcoin/bitcoin/issues/comments/8700945",
      "actor": {
        "login": "dooglus",
        "id": 573356,
        "node_id": "MDQ6VXNlcjU3MzM1Ng==",
        "avatar_url": "https://avatars.githubusercontent.com/u/573356?v=4",
        "gravatar_id": "",
        "url": "https://api.github.com/users/dooglus",
        "html_url": "https://github.com/dooglus",
        "followers_url": "https://api.github.com/users/dooglus/followers",
        "following_url": "https://api.github.com/users/dooglus/following%7B/other_user%7D",
        "gists_url": "https://api.github.com/users/dooglus/gists%7B/gist_id%7D",
        "starred_url": "https://api.github.com/users/dooglus/starred%7B/owner%7D%7B/repo%7D",
        "subscriptions_url": "https://api.github.com/users/dooglus/subscriptions",
        "organizations_url": "https://api.github.com/users/dooglus/orgs",
        "repos_url": "https://api.github.com/users/dooglus/repos",
        "events_url": "https://api.github.com/users/dooglus/events%7B/privacy%7D",
        "received_events_url": "https://api.github.com/users/dooglus/received_events",
        "type": "User",
        "site_admin": false
      },
      "commit_id": null,
      "commit_url": null,
      "created_at": "2012-09-19T18:19:06Z",
      "updated_at": "2012-09-19T18:19:06Z",
      "author_association": "CONTRIBUTOR",
      "body": "I see Pieter's commit fixing the 100% CPU bug in the 0.7.0 code:\n\n```\ncommit f161a2c2114cd7d950248ce75a91ba1923e9abb1\nAuthor: Pieter Wuille <pieter.wuille@gmail.com>\nDate:   Tue Aug 21 17:32:04 2012 +0200\n\n    Fix infinite loops in connection logic\n```\n\nbut nothing implementing \"-noconnect\" (which apparently was never intended to work anyway).\n",
      "user": {
        "login": "dooglus",
        "id": 573356,
        "node_id": "MDQ6VXNlcjU3MzM1Ng==",
        "avatar_url": "https://avatars.githubusercontent.com/u/573356?v=4",
        "gravatar_id": "",
        "url": "https://api.github.com/users/dooglus",
        "html_url": "https://github.com/dooglus",
        "followers_url": "https://api.github.com/users/dooglus/followers",
        "following_url": "https://api.github.com/users/dooglus/following%7B/other_user%7D",
        "gists_url": "https://api.github.com/users/dooglus/gists%7B/gist_id%7D",
        "starred_url": "https://api.github.com/users/dooglus/starred%7B/owner%7D%7B/repo%7D",
        "subscriptions_url": "https://api.github.com/users/dooglus/subscriptions",
        "organizations_url": "https://api.github.com/users/dooglus/orgs",
        "repos_url": "https://api.github.com/users/dooglus/repos",
        "events_url": "https://api.github.com/users/dooglus/events%7B/privacy%7D",
        "received_events_url": "https://api.github.com/users/dooglus/received_events",
        "type": "User",
        "site_admin": false
      },
      "html_url": "https://github.com/bitcoin/bitcoin/issues/1664#issuecomment-8700945",
      "issue_url": "https://api.github.com/repos/bitcoin/bitcoin/issues/1664"
    },
    {
      "event": "commented",
      "id": 8710056,
      "node_id": "MDEyOklzc3VlQ29tbWVudDg3MTAwNTY=",
      "url": "https://api.github.com/repos/bitcoin/bitcoin/issues/comments/8710056",
      "actor": {
        "login": "sipa",
        "id": 548488,
        "node_id": "MDQ6VXNlcjU0ODQ4OA==",
        "avatar_url": "https://avatars.githubusercontent.com/u/548488?v=4",
        "gravatar_id": "",
        "url": "https://api.github.com/users/sipa",
        "html_url": "https://github.com/sipa",
        "followers_url": "https://api.github.com/users/sipa/followers",
        "following_url": "https://api.github.com/users/sipa/following%7B/other_user%7D",
        "gists_url": "https://api.github.com/users/sipa/gists%7B/gist_id%7D",
        "starred_url": "https://api.github.com/users/sipa/starred%7B/owner%7D%7B/repo%7D",
        "subscriptions_url": "https://api.github.com/users/sipa/subscriptions",
        "organizations_url": "https://api.github.com/users/sipa/orgs",
        "repos_url": "https://api.github.com/users/sipa/repos",
        "events_url": "https://api.github.com/users/sipa/events%7B/privacy%7D",
        "received_events_url": "https://api.github.com/users/sipa/received_events",
        "type": "User",
        "site_admin": false
      },
      "commit_id": null,
      "commit_url": null,
      "created_at": "2012-09-19T22:11:32Z",
      "updated_at": "2012-09-19T22:11:32Z",
      "author_association": "MEMBER",
      "body": "Since -connect=X means \"connect only to X\", -noconnect would mean \"don't just connect to one peer\", which is exactly what it does :)\n\nOk, I admit, it wasn't ever considered.\n",
      "user": {
        "login": "sipa",
        "id": 548488,
        "node_id": "MDQ6VXNlcjU0ODQ4OA==",
        "avatar_url": "https://avatars.githubusercontent.com/u/548488?v=4",
        "gravatar_id": "",
        "url": "https://api.github.com/users/sipa",
        "html_url": "https://github.com/sipa",
        "followers_url": "https://api.github.com/users/sipa/followers",
        "following_url": "https://api.github.com/users/sipa/following%7B/other_user%7D",
        "gists_url": "https://api.github.com/users/sipa/gists%7B/gist_id%7D",
        "starred_url": "https://api.github.com/users/sipa/starred%7B/owner%7D%7B/repo%7D",
        "subscriptions_url": "https://api.github.com/users/sipa/subscriptions",
        "organizations_url": "https://api.github.com/users/sipa/orgs",
        "repos_url": "https://api.github.com/users/sipa/repos",
        "events_url": "https://api.github.com/users/sipa/events%7B/privacy%7D",
        "received_events_url": "https://api.github.com/users/sipa/received_events",
        "type": "User",
        "site_admin": false
      },
      "html_url": "https://github.com/bitcoin/bitcoin/issues/1664#issuecomment-8710056",
      "issue_url": "https://api.github.com/repos/bitcoin/bitcoin/issues/1664"
    },
    {
      "event": "commented",
      "id": 8762276,
      "node_id": "MDEyOklzc3VlQ29tbWVudDg3NjIyNzY=",
      "url": "https://api.github.com/repos/bitcoin/bitcoin/issues/comments/8762276",
      "actor": {
        "login": "laanwj",
        "id": 126646,
        "node_id": "MDQ6VXNlcjEyNjY0Ng==",
        "avatar_url": "https://avatars.githubusercontent.com/u/126646?v=4",
        "gravatar_id": "",
        "url": "https://api.github.com/users/laanwj",
        "html_url": "https://github.com/laanwj",
        "followers_url": "https://api.github.com/users/laanwj/followers",
        "following_url": "https://api.github.com/users/laanwj/following%7B/other_user%7D",
        "gists_url": "https://api.github.com/users/laanwj/gists%7B/gist_id%7D",
        "starred_url": "https://api.github.com/users/laanwj/starred%7B/owner%7D%7B/repo%7D",
        "subscriptions_url": "https://api.github.com/users/laanwj/subscriptions",
        "organizations_url": "https://api.github.com/users/laanwj/orgs",
        "repos_url": "https://api.github.com/users/laanwj/repos",
        "events_url": "https://api.github.com/users/laanwj/events%7B/privacy%7D",
        "received_events_url": "https://api.github.com/users/laanwj/received_events",
        "type": "User",
        "site_admin": false
      },
      "commit_id": null,
      "commit_url": null,
      "created_at": "2012-09-21T11:54:48Z",
      "updated_at": "2012-09-21T11:54:48Z",
      "author_association": "MEMBER",
      "body": "`-noconnect` makes no sense. But aren't there other ways already to say \"don't connect to any peers\", or limit the number of outgoing connections? \n",
      "user": {
        "login": "laanwj",
        "id": 126646,
        "node_id": "MDQ6VXNlcjEyNjY0Ng==",
        "avatar_url": "https://avatars.githubusercontent.com/u/126646?v=4",
        "gravatar_id": "",
        "url": "https://api.github.com/users/laanwj",
        "html_url": "https://github.com/laanwj",
        "followers_url": "https://api.github.com/users/laanwj/followers",
        "following_url": "https://api.github.com/users/laanwj/following%7B/other_user%7D",
        "gists_url": "https://api.github.com/users/laanwj/gists%7B/gist_id%7D",
        "starred_url": "https://api.github.com/users/laanwj/starred%7B/owner%7D%7B/repo%7D",
        "subscriptions_url": "https://api.github.com/users/laanwj/subscriptions",
        "organizations_url": "https://api.github.com/users/laanwj/orgs",
        "repos_url": "https://api.github.com/users/laanwj/repos",
        "events_url": "https://api.github.com/users/laanwj/events%7B/privacy%7D",
        "received_events_url": "https://api.github.com/users/laanwj/received_events",
        "type": "User",
        "site_admin": false
      },
      "html_url": "https://github.com/bitcoin/bitcoin/issues/1664#issuecomment-8762276",
      "issue_url": "https://api.github.com/repos/bitcoin/bitcoin/issues/1664"
    },
    {
      "event": "commented",
      "id": 8769408,
      "node_id": "MDEyOklzc3VlQ29tbWVudDg3Njk0MDg=",
      "url": "https://api.github.com/repos/bitcoin/bitcoin/issues/comments/8769408",
      "actor": {
        "login": "dooglus",
        "id": 573356,
        "node_id": "MDQ6VXNlcjU3MzM1Ng==",
        "avatar_url": "https://avatars.githubusercontent.com/u/573356?v=4",
        "gravatar_id": "",
        "url": "https://api.github.com/users/dooglus",
        "html_url": "https://github.com/dooglus",
        "followers_url": "https://api.github.com/users/dooglus/followers",
        "following_url": "https://api.github.com/users/dooglus/following%7B/other_user%7D",
        "gists_url": "https://api.github.com/users/dooglus/gists%7B/gist_id%7D",
        "starred_url": "https://api.github.com/users/dooglus/starred%7B/owner%7D%7B/repo%7D",
        "subscriptions_url": "https://api.github.com/users/dooglus/subscriptions",
        "organizations_url": "https://api.github.com/users/dooglus/orgs",
        "repos_url": "https://api.github.com/users/dooglus/repos",
        "events_url": "https://api.github.com/users/dooglus/events%7B/privacy%7D",
        "received_events_url": "https://api.github.com/users/dooglus/received_events",
        "type": "User",
        "site_admin": false
      },
      "commit_id": null,
      "commit_url": null,
      "created_at": "2012-09-21T16:02:25Z",
      "updated_at": "2012-09-21T16:02:25Z",
      "author_association": "CONTRIBUTOR",
      "body": "I've used \"-connect=127.0.0.1\" in the past to get no connections.\n\nI'm wondering whether \"-maxconnections=0\" would work too:\n\n```\nStarting program: /home/chris/Bin/bitcoin -maxconnections=0\n[...]\nBitcoin version v0.7.0rc3-dirty-beta (2012-09-12 14:07:22 -0400)\n[...]\nsend version message: version 60002, blocks=199858, us=0.0.0.0:0, them=0.0.0.0:0, peer=127.0.0.1:0\n[...]\nCTxMemPool::accept() : accepted 058cdc9c4d (poolsz 1)\n[...]\nAdded 4 addresses from 178.18.90.41: 1646 tried, 12503 new\nAdded 4 addresses from 87.155.86.94: 1646 tried, 12506 new\nAdded 4 addresses from 173.242.112.53: 1646 tried, 12507 new\n[...]\nAdded 3 addresses from ::: 1646 tried, 12508 new\n94 addresses found from DNS seeds\nThreadDNSAddressSeed exited\n```\n\nThe GUI says \"0 active connections\" but the log (above) appears to show some communication with peers, so I'm a bit confused about what's going on there.\n",
      "user": {
        "login": "dooglus",
        "id": 573356,
        "node_id": "MDQ6VXNlcjU3MzM1Ng==",
        "avatar_url": "https://avatars.githubusercontent.com/u/573356?v=4",
        "gravatar_id": "",
        "url": "https://api.github.com/users/dooglus",
        "html_url": "https://github.com/dooglus",
        "followers_url": "https://api.github.com/users/dooglus/followers",
        "following_url": "https://api.github.com/users/dooglus/following%7B/other_user%7D",
        "gists_url": "https://api.github.com/users/dooglus/gists%7B/gist_id%7D",
        "starred_url": "https://api.github.com/users/dooglus/starred%7B/owner%7D%7B/repo%7D",
        "subscriptions_url": "https://api.github.com/users/dooglus/subscriptions",
        "organizations_url": "https://api.github.com/users/dooglus/orgs",
        "repos_url": "https://api.github.com/users/dooglus/repos",
        "events_url": "https://api.github.com/users/dooglus/events%7B/privacy%7D",
        "received_events_url": "https://api.github.com/users/dooglus/received_events",
        "type": "User",
        "site_admin": false
      },
      "html_url": "https://github.com/bitcoin/bitcoin/issues/1664#issuecomment-8769408",
      "issue_url": "https://api.github.com/repos/bitcoin/bitcoin/issues/1664"
    },
    {
      "event": "commented",
      "id": 8770053,
      "node_id": "MDEyOklzc3VlQ29tbWVudDg3NzAwNTM=",
      "url": "https://api.github.com/repos/bitcoin/bitcoin/issues/comments/8770053",
      "actor": {
        "login": "dooglus",
        "id": 573356,
        "node_id": "MDQ6VXNlcjU3MzM1Ng==",
        "avatar_url": "https://avatars.githubusercontent.com/u/573356?v=4",
        "gravatar_id": "",
        "url": "https://api.github.com/users/dooglus",
        "html_url": "https://github.com/dooglus",
        "followers_url": "https://api.github.com/users/dooglus/followers",
        "following_url": "https://api.github.com/users/dooglus/following%7B/other_user%7D",
        "gists_url": "https://api.github.com/users/dooglus/gists%7B/gist_id%7D",
        "starred_url": "https://api.github.com/users/dooglus/starred%7B/owner%7D%7B/repo%7D",
        "subscriptions_url": "https://api.github.com/users/dooglus/subscriptions",
        "organizations_url": "https://api.github.com/users/dooglus/orgs",
        "repos_url": "https://api.github.com/users/dooglus/repos",
        "events_url": "https://api.github.com/users/dooglus/events%7B/privacy%7D",
        "received_events_url": "https://api.github.com/users/dooglus/received_events",
        "type": "User",
        "site_admin": false
      },
      "commit_id": null,
      "commit_url": null,
      "created_at": "2012-09-21T16:24:44Z",
      "updated_at": "2012-09-21T16:24:44Z",
      "author_association": "CONTRIBUTOR",
      "body": "In particular, my client somehow received notification of a payment to one of my addresses (not a payment to self) while I was running with \"-maxconnections=0\".  How can that happen?\n\n```\nCTxMemPool::accept() : accepted 058cdc9c4d (poolsz 1)\n```\n\nWhen I try sending a payment it doesn't send, as expected:\n\n```\nStatus: 0/unconfirmed, has not been successfully broadcast yet\nDate: 12-09-21 09:22\nTo: satoshidice lessthan 8000 1dice6YgEVBf88erBFra9BHf6ZMoyvG88\n```\n\nbut for some reason I was able to receive a payment.\n",
      "user": {
        "login": "dooglus",
        "id": 573356,
        "node_id": "MDQ6VXNlcjU3MzM1Ng==",
        "avatar_url": "https://avatars.githubusercontent.com/u/573356?v=4",
        "gravatar_id": "",
        "url": "https://api.github.com/users/dooglus",
        "html_url": "https://github.com/dooglus",
        "followers_url": "https://api.github.com/users/dooglus/followers",
        "following_url": "https://api.github.com/users/dooglus/following%7B/other_user%7D",
        "gists_url": "https://api.github.com/users/dooglus/gists%7B/gist_id%7D",
        "starred_url": "https://api.github.com/users/dooglus/starred%7B/owner%7D%7B/repo%7D",
        "subscriptions_url": "https://api.github.com/users/dooglus/subscriptions",
        "organizations_url": "https://api.github.com/users/dooglus/orgs",
        "repos_url": "https://api.github.com/users/dooglus/repos",
        "events_url": "https://api.github.com/users/dooglus/events%7B/privacy%7D",
        "received_events_url": "https://api.github.com/users/dooglus/received_events",
        "type": "User",
        "site_admin": false
      },
      "html_url": "https://github.com/bitcoin/bitcoin/issues/1664#issuecomment-8770053",
      "issue_url": "https://api.github.com/repos/bitcoin/bitcoin/issues/1664"
    },
    {
      "event": "commented",
      "id": 27141654,
      "node_id": "MDEyOklzc3VlQ29tbWVudDI3MTQxNjU0",
      "url": "https://api.github.com/repos/bitcoin/bitcoin/issues/comments/27141654",
      "actor": {
        "login": "laanwj",
        "id": 126646,
        "node_id": "MDQ6VXNlcjEyNjY0Ng==",
        "avatar_url": "https://avatars.githubusercontent.com/u/126646?v=4",
        "gravatar_id": "",
        "url": "https://api.github.com/users/laanwj",
        "html_url": "https://github.com/laanwj",
        "followers_url": "https://api.github.com/users/laanwj/followers",
        "following_url": "https://api.github.com/users/laanwj/following%7B/other_user%7D",
        "gists_url": "https://api.github.com/users/laanwj/gists%7B/gist_id%7D",
        "starred_url": "https://api.github.com/users/laanwj/starred%7B/owner%7D%7B/repo%7D",
        "subscriptions_url": "https://api.github.com/users/laanwj/subscriptions",
        "organizations_url": "https://api.github.com/users/laanwj/orgs",
        "repos_url": "https://api.github.com/users/laanwj/repos",
        "events_url": "https://api.github.com/users/laanwj/events%7B/privacy%7D",
        "received_events_url": "https://api.github.com/users/laanwj/received_events",
        "type": "User",
        "site_admin": false
      },
      "commit_id": null,
      "commit_url": null,
      "created_at": "2013-10-26T08:02:53Z",
      "updated_at": "2013-10-26T08:02:53Z",
      "author_association": "MEMBER",
      "body": "The CPU issue was solved, and `mapMultiArgs[\"-connect\"].size() > 0` was added, so closing\n",
      "user": {
        "login": "laanwj",
        "id": 126646,
        "node_id": "MDQ6VXNlcjEyNjY0Ng==",
        "avatar_url": "https://avatars.githubusercontent.com/u/126646?v=4",
        "gravatar_id": "",
        "url": "https://api.github.com/users/laanwj",
        "html_url": "https://github.com/laanwj",
        "followers_url": "https://api.github.com/users/laanwj/followers",
        "following_url": "https://api.github.com/users/laanwj/following%7B/other_user%7D",
        "gists_url": "https://api.github.com/users/laanwj/gists%7B/gist_id%7D",
        "starred_url": "https://api.github.com/users/laanwj/starred%7B/owner%7D%7B/repo%7D",
        "subscriptions_url": "https://api.github.com/users/laanwj/subscriptions",
        "organizations_url": "https://api.github.com/users/laanwj/orgs",
        "repos_url": "https://api.github.com/users/laanwj/repos",
        "events_url": "https://api.github.com/users/laanwj/events%7B/privacy%7D",
        "received_events_url": "https://api.github.com/users/laanwj/received_events",
        "type": "User",
        "site_admin": false
      },
      "html_url": "https://github.com/bitcoin/bitcoin/issues/1664#issuecomment-27141654",
      "issue_url": "https://api.github.com/repos/bitcoin/bitcoin/issues/1664"
    },
    {
      "event": "closed",
      "id": 72429286,
      "node_id": "MDExOkNsb3NlZEV2ZW50NzI0MjkyODY=",
      "url": "https://api.github.com/repos/bitcoin/bitcoin/issues/events/72429286",
      "actor": {
        "login": "laanwj",
        "id": 126646,
        "node_id": "MDQ6VXNlcjEyNjY0Ng==",
        "avatar_url": "https://avatars.githubusercontent.com/u/126646?v=4",
        "gravatar_id": "",
        "url": "https://api.github.com/users/laanwj",
        "html_url": "https://github.com/laanwj",
        "followers_url": "https://api.github.com/users/laanwj/followers",
        "following_url": "https://api.github.com/users/laanwj/following%7B/other_user%7D",
        "gists_url": "https://api.github.com/users/laanwj/gists%7B/gist_id%7D",
        "starred_url": "https://api.github.com/users/laanwj/starred%7B/owner%7D%7B/repo%7D",
        "subscriptions_url": "https://api.github.com/users/laanwj/subscriptions",
        "organizations_url": "https://api.github.com/users/laanwj/orgs",
        "repos_url": "https://api.github.com/users/laanwj/repos",
        "events_url": "https://api.github.com/users/laanwj/events%7B/privacy%7D",
        "received_events_url": "https://api.github.com/users/laanwj/received_events",
        "type": "User",
        "site_admin": false
      },
      "commit_id": null,
      "commit_url": null,
      "created_at": "2013-10-26T08:02:54Z"
    },
    {
      "event": "referenced",
      "id": 1372009941,
      "node_id": "MDE1OlJlZmVyZW5jZWRFdmVudDEzNzIwMDk5NDE=",
      "url": "https://api.github.com/repos/bitcoin/bitcoin/issues/events/1372009941",
      "actor": {
        "login": "suprnurd",
        "id": 21205640,
        "node_id": "MDQ6VXNlcjIxMjA1NjQw",
        "avatar_url": "https://avatars.githubusercontent.com/u/21205640?v=4",
        "gravatar_id": "",
        "url": "https://api.github.com/users/suprnurd",
        "html_url": "https://github.com/suprnurd",
        "followers_url": "https://api.github.com/users/suprnurd/followers",
        "following_url": "https://api.github.com/users/suprnurd/following%7B/other_user%7D",
        "gists_url": "https://api.github.com/users/suprnurd/gists%7B/gist_id%7D",
        "starred_url": "https://api.github.com/users/suprnurd/starred%7B/owner%7D%7B/repo%7D",
        "subscriptions_url": "https://api.github.com/users/suprnurd/subscriptions",
        "organizations_url": "https://api.github.com/users/suprnurd/orgs",
        "repos_url": "https://api.github.com/users/suprnurd/repos",
        "events_url": "https://api.github.com/users/suprnurd/events%7B/privacy%7D",
        "received_events_url": "https://api.github.com/users/suprnurd/received_events",
        "type": "User",
        "site_admin": false
      },
      "commit_id": "8c1e5e83841ee4b4004764f44c281ac0b163a65e",
      "commit_url": "https://api.github.com/repos/chaincoin-legacy/chaincoin/commits/8c1e5e83841ee4b4004764f44c281ac0b163a65e",
      "created_at": "2017-12-05T06:49:57Z"
    },
    {
      "event": "locked",
      "id": 5272000454,
      "node_id": "LOE_lADOABII584AXVf2zwAAAAE6PFfG",
      "url": "https://api.github.com/repos/bitcoin/bitcoin/issues/events/5272000454",
      "actor": {
        "login": "DrahtBot",
        "id": 39886733,
        "node_id": "MDQ6VXNlcjM5ODg2NzMz",
        "avatar_url": "https://avatars.githubusercontent.com/u/39886733?v=4",
        "gravatar_id": "",
        "url": "https://api.github.com/users/DrahtBot",
        "html_url": "https://github.com/DrahtBot",
        "followers_url": "https://api.github.com/users/DrahtBot/followers",
        "following_url": "https://api.github.com/users/DrahtBot/following%7B/other_user%7D",
        "gists_url": "https://api.github.com/users/DrahtBot/gists%7B/gist_id%7D",
        "starred_url": "https://api.github.com/users/DrahtBot/starred%7B/owner%7D%7B/repo%7D",
        "subscriptions_url": "https://api.github.com/users/DrahtBot/subscriptions",
        "organizations_url": "https://api.github.com/users/DrahtBot/orgs",
        "repos_url": "https://api.github.com/users/DrahtBot/repos",
        "events_url": "https://api.github.com/users/DrahtBot/events%7B/privacy%7D",
        "received_events_url": "https://api.github.com/users/DrahtBot/received_events",
        "type": "User",
        "site_admin": false
      },
      "commit_id": null,
      "commit_url": null,
      "created_at": "2021-09-08T12:32:15Z",
      "lock_reason": "resolved"
    }
  ]
}